LICENSE
MANIFEST.in
README.md
pyproject.toml
requirements.txt
setup.py
rii/__init__.py
rii/rii.py
rii.egg-info/PKG-INFO
rii.egg-info/SOURCES.txt
rii.egg-info/dependency_links.txt
rii.egg-info/not-zip-safe
rii.egg-info/requires.txt
rii.egg-info/top_level.txt
src/distance.h
src/main.cpp
src/pqkmeans.cpp
src/pqkmeans.h
src/rii.h
src/extern/sse2neon.h
tests/__init__.py
tests/context.py
tests/test_rii.py