Metadata-Version: 2.4
Name: rii
Version: 0.2.12
Summary: Fast and memory-efficient ANN with a subset-search functionality
Home-page: https://github.com/matsui528/rii
Author: Yusuke Matsui
Author-email: matsui528@gmail.com
License: MIT
Requires-Python: >=3.6
License-File: LICENSE
Requires-Dist: pybind11>=2.9
Requires-Dist: nanopq
Dynamic: author
Dynamic: author-email
Dynamic: description
Dynamic: description-content-type
Dynamic: home-page
Dynamic: license
Dynamic: license-file
Dynamic: requires-dist
Dynamic: requires-python
Dynamic: summary
